[
  {
    "__type__": "cc.SpriteFrame",
    "content": {
      "name": "0010",
      "texture": "119T9zf0ZEjZ18qb9bXJXN",
      "rect": [
        0,
        0,
        93,
        37
      ],
      "offset": [
        0,
        0
      ],
      "originalSize": [
        93,
        37
      ],
      "capInsets": [
        0,
        0,
        0,
        0
      ]
    }
  },
  [
    {
      "__type__": "cc.Prefab",
      "_name": "0010",
      "data": {
        "__id__": 1
      }
    },
    {
      "__type__": "cc.Node",
      "_name": "0010",
      "_components": [
        {
          "__type__": "cc.Sprite",
          "node": {
            "__id__": 1
          },
          "_spriteFrame": {
            "__uuid__": "1cus+VcDRGLZNVeAcP01kh"
          }
        }
      ],
      "_prefab": {
        "__type__": "cc.PrefabInfo",
        "root": {
          "__id__": 1
        },
        "asset": {
          "__id__": 0
        },
        "fileId": "4dr8FcSilLxpulvK+yxr84"
      },
      "_contentSize": {
        "__type__": "cc.Size",
        "width": 93,
        "height": 37
      },
      "_trs": {
        "__type__": "TypedArray",
        "ctor": "Float64Array",
        "array": [
          0,
          0,
          0,
          0,
          0,
          0,
          1,
          1,
          1,
          1
        ]
      }
    }
  ]
]